WaifuPicsPython/__init__.py
WaifuPicsPython/async_session.py
WaifuPicsPython/sync_session.py
WaifuPicsPython/variables.py
WaifuPicsPython-0.2.0.dist-info/LICENSE
WaifuPicsPython-0.2.0.dist-info/METADATA
WaifuPicsPython-0.2.0.dist-info/WHEEL
WaifuPicsPython-0.2.0.dist-info/top_level.txt
WaifuPicsPython-0.2.0.dist-info/RECORD
