Metadata-Version: 2.1
Name: WaifuPicsPython
Version: 0.2.0
Summary: An asyncronous & syncronous API wrapper for https://waifu.pics written in Python.
Home-page: https://github.com/Scrumpyy/WaifuPicsPython
Author: Scrumpyy
Author-email: scrumpy@weeb.email
License: UNKNOWN
Project-URL: Bug Tracker, https://github.com/Scrumpyy/WaifuPicsPython/issues
Platform: UNKNOWN
Classifier: Programming Language :: Python :: 3
Classifier: License :: OSI Approved :: MIT License
Classifier: Operating System :: OS Independent
Requires-Python: >=3.6
License-File: LICENSE
